whisper_client/__about__.py
whisper_client/__init__.py
whisper_client/cli.py
whisper_client/extractAudio.py
whisper_client/file_finder.py
whisper_client/main.py
whisper_client-0.5.1.dist-info/METADATA
whisper_client-0.5.1.dist-info/WHEEL
whisper_client-0.5.1.dist-info/entry_points.txt
whisper_client-0.5.1.dist-info/licenses/LICENSE.txt
whisper_client-0.5.1.dist-info/RECORD
