Metadata-Version: 2.3
Name: whisper-client
Version: 0.5.1
Summary: A REST client for the whisper-api
Project-URL: Documentation, https://github.com/Marceau-h/whisper-client#readme
Project-URL: Issues, https://github.com/Marceau-h/whisper-client/issues
Project-URL: Source, https://github.com/Marceau-h/whisper-client
Author-email: Marceau-h <pypi@marceau-h.fr>
License: AGPL-3.0
Classifier: Development Status :: 4 - Beta
Classifier: Programming Language :: Python
Classifier: Programming Language :: Python :: 3.7
Classifier: Programming Language :: Python :: 3.8
Classifier: Programming Language :: Python :: 3.9
Classifier: Programming Language :: Python :: 3.10
Classifier: Programming Language :: Python :: 3.11
Classifier: Programming Language :: Python :: Implementation :: CPython
Classifier: Programming Language :: Python :: Implementation :: PyPy
Requires-Python: >=3.7
Requires-Dist: httpx
Requires-Dist: tqdm
